contiguous_params/__init__.py
contiguous_params/params.py
contiguous_params-1.0.0.dist-info/METADATA
contiguous_params-1.0.0.dist-info/WHEEL
contiguous_params-1.0.0.dist-info/top_level.txt
contiguous_params-1.0.0.dist-info/zip-safe
contiguous_params-1.0.0.dist-info/RECORD
