Metadata-Version: 2.1
Name: contiguous-params
Version: 1.0.0
Summary: Make pytorch parameters contiguous to speed up training by 100x.
Home-page: http://www.github.com/philjd/contiguous_pytorch_params
Author: Philipp Jund
Author-email: ijund.phil@gmail.com
License: Apache 2.0
Download-URL: http://www.github.com/philjd/contiguous_pytorch_params/tags
Keywords: pytorch,contiguous,parameters,speed up,accelerate
Platform: UNKNOWN
Classifier: Development Status :: 5 - Production/Stable
Classifier: Intended Audience :: Developers
Classifier: Intended Audience :: Science/Research
Classifier: License :: OSI Approved :: Apache Software License
Classifier: Natural Language :: English
Classifier: Operating System :: OS Independent
Classifier: Programming Language :: Python :: 3
Classifier: Programming Language :: Python :: 3.6
Classifier: Programming Language :: Python :: 3.7
Classifier: Topic :: Scientific/Engineering
Classifier: Topic :: Scientific/Engineering :: Mathematics
Classifier: Topic :: Scientific/Engineering :: Artificial Intelligence
Classifier: Topic :: Software Development
Classifier: Topic :: Software Development :: Libraries
Classifier: Topic :: Software Development :: Libraries :: Python Modules
Requires-Python: >=3.6.0
Requires-Dist: torch (>=1.5.1)
